magritte/__init__.py
magritte/build.py
magritte/cli.py
magritte/copy_files.py
magritte/db.py
magritte/settings.py
magritte/tests.py
magritte-0.2.0.dist-info/DESCRIPTION.rst
magritte-0.2.0.dist-info/METADATA
magritte-0.2.0.dist-info/RECORD
magritte-0.2.0.dist-info/WHEEL
magritte-0.2.0.dist-info/entry_points.txt
magritte-0.2.0.dist-info/metadata.json
magritte-0.2.0.dist-info/top_level.txt
